[
	{
	"eventID": "01",
        "creatorID": "02", //user ID
        "title": "Study Jam",
        "duration": "2:00:00",
        "constraint": ["Apr 19", "Apr 21"], // constrained range: 1-5 days
        "notes": "",
        "participants": {"01":"pending",
			 "02":"accepted",
			 "03":"rejected"},
        "timeList": {"01":{"date":"Apr 19", "startTime": "16:00:00", "endTime": "18:00:00"},
		     "02":{"date":"Apr 19", "startTime": "18:00:00", "endTime": "20:00:00"},
		     "03":{"date":"Apr 20", "startTime": "18:00:00", "endTime": "20:00:00"}},  //default: pacific time; 24h
	"preference": {"01": 3,
		       "02": 1,
		       "03": 0} // when timelist is finished, generate based on slotIDs and define value 0
	},
	{
        "eventID": "02",
        "creatorID": "03", //user ID
        "title": "Rock Climbing",
        "duration": "1:30:00",
        "constraint": ["July 30", "Aug 2"], // constrained range: 1-5 days
        "notes": "",
        "participants": {"03":"pending",
			 "04":"pending",
			 "06":"rejected",
			 "09":"accepted"},
        "timeList": {"01":{"date":"July 30", "startTime": "12:00:00", "endTime": "13:00:00"},
		     "02":{"date":"July 19", "startTime": "14:30:00", "endTime": "15:30:00"},
		     "03":{"date":"Aug 1", "startTime": "12:00:00", "endTime": "13:00:00"}},
		     "04":{"date":"Aug 2", "startTime": "09:00:00", "endTime": "10:00:00"},  //default: pacific time; 24h
	"preference": {"01": 3,
		       "02": 1,
		       "03": 0, 
		       "04": 3} // when timelist is finished, generate based on slotIDs and define value 0
	},
	{
		
    
    
	},
	{
		
    
    
	},
	{
		
    
    
	}
]
